{"about.md":"BSboIcyU","books_high_performance_chapter8.md":"ITm926mv","books_high_performance_chapter10.md":"wZDsy-I6","books_index.md":"BLxD5Uqq","books_high_performance_chapter3.md":"BtZ-pXG2","books_high_performance_chapter5.md":"N84vldlY","books_high_performance_chapter7.md":"BLBN9CJL","books_high_performance_chapter6.md":"BPX1pwJk","demo_api-examples.md":"Cs63GTWo","demo_markdown-examples.md":"DcrTp_Pl","efficiency_demo.md":"CpQvpv33","efficiency_google_google.md":"CryPNf9K","efficiency_vscode_copilot.md":"DaDAJcnE","efficiency_index.md":"DTq44DD-","frontend_css_clamp.md":"CLX3JG0H","books_high_performance_chapter1.md":"Bd7d-CIj","books_high_performance_chapter2.md":"iqbATnVV","frontend_css_margin-inline.md":"TblNknzM","books_high_performance_chapter11.md":"BNFjAu4e","readme.md":"DkmsgcTG","frontend_css_sass.md":"DKVoohb1","frontend_engineering_editorconfig.md":"CXvJlZPr","books_high_performance_hashtable.md":"0VajavnB","frontend_demo.md":"DoFtF0s2","frontend_engineering_mockdata.md":"BeAf7oFS","frontend_engineering_prettierrc.md":"BTDZP1dD","frontend_engineering_git.md":"DZBW4ZzT","frontend_engineering_browserslistrc.md":"48bPFnbE","frontend_engineering_eslintrc.md":"DtyABKiX","frontend_engineering_prettierignore.md":"BrMetXD2","frontend_index.md":"DqeADPAQ","books_high_performance_chapter4.md":"DT3alvwf","frontend_vue_composition.md":"l52J8tjl","frontend_others_secure.md":"dbDAOzTl","frontend_others_target.md":"BNhB0v9F","frontend_others_projecthandover.md":"BITRjDqr","index.md":"BtfTILSg","frontend_weixin_miniprogramlife.md":"DXA05g_U","frontend_engineering_terminalsize.md":"DeecO5cM","frontend_html_imglazy.md":"CsMMeW2P","books_high_performance_chapter9.md":"BpxinbuX","frontend_vue_style.md":"mqyorNba","frontend_css_center.md":"CVePjMWE","frontend_engineering_gitignore.md":"K-fosyjl","frontend_api-examples.md":"DRxsgr6u","frontend_markdown-examples.md":"BL9OpGhv","frontend_npm_taobao.md":"Bos_04uP","frontend_engineering_eslintignore.md":"B80AWsJ3","frontend_npm_transfer.md":"CJXcKM5F","frontend_css_style.md":"BsFMhKZJ","frontend_html_style.md":"1BgwKid1","frontend_css_mask.md":"D0ISMcQ7","frontend_javascript_style.md":"53-75Lbx","frontend_engineering_npmrc.md":"D6UlyQxO"}
